randomcontent/__init__.py
randomcontent/generators/__init__.py
randomcontent/generators/identifier_generator.py
randomcontent/generators/number_generator.py
randomcontent/generators/structured_generator.py
randomcontent/generators/text_generator.py
randomcontent/utils/__init__.py
randomcontent/utils/data_utils.py
randomcontent/utils/template_utils.py
tests/__init__.py
tests/test_generators.py
randomcontent-1.0.2.dist-info/LICENSE.txt
randomcontent-1.0.2.dist-info/METADATA
randomcontent-1.0.2.dist-info/WHEEL
randomcontent-1.0.2.dist-info/top_level.txt
randomcontent-1.0.2.dist-info/RECORD
