Metadata-Version: 2.1
Name: randomcontent
Version: 1.0.2
Summary: A library for generating random text, numbers, and structured data.
Home-page: https://github.com/prafulacharya/randomcontent
Author: Praful B Shankar
Author-email: prafulvishwakarmaq@gmail.com
Classifier: Programming Language :: Python :: 3
Classifier: License :: OSI Approved :: MIT License
Classifier: Operating System :: OS Independent
Requires-Python: >=3.10
License-File: LICENSE.txt
